workflows_mcp/__init__.py
workflows_mcp/__main__.py
workflows_mcp/context.py
workflows_mcp/formatting.py
workflows_mcp/server.py
workflows_mcp/tools.py
workflows_mcp/engine/__init__.py
workflows_mcp/engine/block.py
workflows_mcp/engine/block_status.py
workflows_mcp/engine/block_utils.py
workflows_mcp/engine/context_vars.py
workflows_mcp/engine/dag.py
workflows_mcp/engine/exceptions.py
workflows_mcp/engine/execution.py
workflows_mcp/engine/execution_context.py
workflows_mcp/engine/execution_result.py
workflows_mcp/engine/executor_base.py
workflows_mcp/engine/executors_core.py
workflows_mcp/engine/executors_file.py
workflows_mcp/engine/executors_http.py
workflows_mcp/engine/executors_interactive.py
workflows_mcp/engine/executors_llm.py
workflows_mcp/engine/executors_state.py
workflows_mcp/engine/executors_workflow.py
workflows_mcp/engine/file_outline.py
workflows_mcp/engine/interpolation.py
workflows_mcp/engine/io_queue.py
workflows_mcp/engine/job_queue.py
workflows_mcp/engine/job_store.py
workflows_mcp/engine/llm_config.py
workflows_mcp/engine/load_result.py
workflows_mcp/engine/loader.py
workflows_mcp/engine/metadata.py
workflows_mcp/engine/orchestrator.py
workflows_mcp/engine/registry.py
workflows_mcp/engine/schema.py
workflows_mcp/engine/state_config.py
workflows_mcp/engine/validation.py
workflows_mcp/engine/workflow_runner.py
workflows_mcp/engine/resolver/__init__.py
workflows_mcp/engine/resolver/classifier.py
workflows_mcp/engine/resolver/proxies.py
workflows_mcp/engine/resolver/rules.py
workflows_mcp/engine/resolver/security_rules.py
workflows_mcp/engine/resolver/syntax_rules.py
workflows_mcp/engine/resolver/unified_resolver.py
workflows_mcp/engine/secrets/__init__.py
workflows_mcp/engine/secrets/audit.py
workflows_mcp/engine/secrets/exceptions.py
workflows_mcp/engine/secrets/provider.py
workflows_mcp/engine/secrets/redactor.py
workflows_mcp/templates/README.md
workflows_mcp/templates/ci/conditional-deploy.yaml
workflows_mcp-7.1.0.dist-info/METADATA
workflows_mcp-7.1.0.dist-info/WHEEL
workflows_mcp-7.1.0.dist-info/entry_points.txt
workflows_mcp-7.1.0.dist-info/licenses/LICENSE
workflows_mcp-7.1.0.dist-info/RECORD
