Metadata-Version: 2.4
Name: workflows-mcp
Version: 7.1.0
Summary: MCP server for DAG-based workflow execution with YAML definitions and LLM collaboration
Project-URL: Homepage, https://github.com/qtsone/workflows-mcp
Project-URL: Repository, https://github.com/qtsone/workflows-mcp
Project-URL: Documentation, https://github.com/qtsone/workflows-mcp/blob/main/README.md
Project-URL: Issues, https://github.com/qtsone/workflows-mcp/issues
Project-URL: Changelog, https://github.com/qtsone/workflows-mcp/blob/main/CHANGELOG.md
Author-email: Iulian Bacalu <ibacalu@icloud.com>
License-Expression: AGPL-3.0-or-later
License-File: LICENSE
Keywords: automation,claude,dag,llm-collaboration,mcp,workflow
Classifier: Development Status :: 5 - Production/Stable
Classifier: Intended Audience :: Developers
Classifier: License :: OSI Approved :: GNU Affero General Public License v3 or later (AGPLv3+)
Classifier: Programming Language :: Python :: 3
Classifier: Programming Language :: Python :: 3.12
Classifier: Topic :: Software Development :: Libraries :: Python Modules
Classifier: Topic :: System :: Distributed Computing
Requires-Python: >=3.12
Requires-Dist: jinja2>=3.1.0
Requires-Dist: jsonschema>=4.0
Requires-Dist: mcp[cli]>=1.0.0
Requires-Dist: openai>=1.68.0
Requires-Dist: pathspec>=0.12.0
Requires-Dist: pydantic>=2.0
Requires-Dist: pyyaml>=6.0
Requires-Dist: tree-sitter-languages>=1.10.0
Requires-Dist: types-pyyaml>=6.0.12.20250915
Provides-Extra: dev
Requires-Dist: mypy>=1.8; extra == 'dev'
Requires-Dist: pytest-asyncio>=0.21.0; extra == 'dev'
Requires-Dist: pytest-cov>=4.0; extra == 'dev'
Requires-Dist: pytest>=8.0; extra == 'dev'
Requires-Dist: ruff>=0.1.0; extra == 'dev'
